ugent_food/__init__.py
ugent_food/__main__.py
ugent_food/api/__init__.py
ugent_food/api/enums.py
ugent_food/api/models.py
ugent_food/api/wrapper.py
ugent_food/cli/__init__.py
ugent_food/cli/app.py
ugent_food/cli/async_command.py
ugent_food/cli/config.py
ugent_food/cli/default_group.py
ugent_food/cli/parsers.py
ugent_food/cli/tables.py
ugent_food/exceptions/__init__.py
ugent_food/exceptions/api_exception.py
ugent_food/exceptions/base.py
ugent_food/exceptions/no_menu_found.py
ugent_food/i18n.py
ugent_food/version.py
ugent_food-1.1.0.dist-info/entry_points.txt
ugent_food-1.1.0.dist-info/LICENSE
ugent_food-1.1.0.dist-info/WHEEL
ugent_food-1.1.0.dist-info/METADATA
ugent_food-1.1.0.dist-info/RECORD
