Metadata-Version: 2.1
Name: ugent-food
Version: 1.1.0
Summary: Command-line tool to get the current menu for Ghent University restaurants
Home-page: https://github.com/stijndcl/ugent-food
License: MIT
Keywords: python, food, api, wrapper, zeus, hydra, ugent, ghent, university, resto, restaurants, menu
Author: stijndcl
Requires-Python: >=3.9,<4.0
Classifier: Development Status :: 3 - Alpha
Classifier: Intended Audience :: Developers
Classifier: License :: OSI Approved :: MIT License
Classifier: Natural Language :: Dutch
Classifier: Natural Language :: English
Classifier: Operating System :: OS Independent
Classifier: Programming Language :: Python :: 3
Classifier: Programming Language :: Python :: 3.10
Classifier: Programming Language :: Python :: 3.9
Classifier: Topic :: Software Development :: Libraries
Classifier: Topic :: Software Development :: Libraries :: Python Modules
Classifier: Topic :: Utilities
Classifier: Typing :: Typed
Requires-Dist: aiohttp (>=3.8.1,<4.0.0)
Requires-Dist: click (>=8.1.3,<9.0.0)
Requires-Dist: dacite (>=1.6.0,<2.0.0)
Requires-Dist: tabulate (>=0.8.10,<0.9.0)
Project-URL: Repository, https://github.com/stijndcl/ugent-food
Project-URL: issues, https://github.com/stijndcl/ugent-food/issues
